tests/__init__.py
tests/test_hello_world_tool.py
yao_hello_world_default/__init__.py
yao_hello_world_default/tools/__init__.py
yao_hello_world_default/tools/hello_world_tool.py
yao_hello_world_default/tools/utils.py
yao_hello_world_default/yamls/hello_world_tool.yaml
yao_hello_world_default-0.0.1.dist-info/METADATA
yao_hello_world_default-0.0.1.dist-info/WHEEL
yao_hello_world_default-0.0.1.dist-info/entry_points.txt
yao_hello_world_default-0.0.1.dist-info/top_level.txt
yao_hello_world_default-0.0.1.dist-info/RECORD
