Metadata-Version: 2.1
Name: yao-hello-world-default
Version: 0.0.1
Summary: This is my tools package
